{
  "animation": "anger_hit", 
  "frame_list": [
    {
      "positions": [
        {
          "dof": "tower_1", 
          "pos": 4.885676821340682
        }, 
        {
          "dof": "tower_3", 
          "pos": 4.371280300504985
        }, 
        {
          "dof": "tower_2", 
          "pos": 4.578686252864914
        }, 
        {
          "dof": "base", 
          "pos": 2.995104274703519
        }, 
        {
          "dof": "ears", 
          "pos": 5.0
        }
      ], 
      "millis": 0.0
    }, 
    {
      "positions": [
        {
          "dof": "tower_1", 
          "pos": 4.817889646424232
        }, 
        {
          "dof": "tower_3", 
          "pos": 4.412327942832928
        }, 
        {
          "dof": "tower_2", 
          "pos": 4.604988108203766
        }, 
        {
          "dof": "base", 
          "pos": 2.9960511682356463
        }, 
        {
          "dof": "ears", 
          "pos": 5.0
        }
      ], 
      "millis": 102.0
    }, 
    {
      "positions": [
        {
          "dof": "tower_1", 
          "pos": 4.776783496009665
        }, 
        {
          "dof": "tower_3", 
          "pos": 4.42498846253484
        }, 
        {
          "dof": "tower_2", 
          "pos": 4.6343789164760505
        }, 
        {
          "dof": "base", 
          "pos": 2.9759788378379834
        }, 
        {
          "dof": "ears", 
          "pos": 5.0
        }
      ], 
      "millis": 203.0
    }, 
    {
      "positions": [
        {
          "dof": "tower_1", 
          "pos": 4.685931013111865
        }, 
        {
          "dof": "tower_3", 
          "pos": 4.471187834702837
        }, 
        {
          "dof": "tower_2", 
          "pos": 4.678887095649513
        }, 
        {
          "dof": "base", 
          "pos": 2.9480094513081276
        }, 
        {
          "dof": "ears", 
          "pos": 5.0
        }
      ], 
      "millis": 308.0
    }, 
    {
      "positions": [
        {
          "dof": "tower_1", 
          "pos": 4.547085007809496
        }, 
        {
          "dof": "tower_3", 
          "pos": 4.510375599450223
        }, 
        {
          "dof": "tower_2", 
          "pos": 4.7785356530185386
        }, 
        {
          "dof": "base", 
          "pos": 2.945903719611014
        }, 
        {
          "dof": "ears", 
          "pos": 5.0
        }
      ], 
      "millis": 410.0
    }, 
    {
      "positions": [
        {
          "dof": "tower_1", 
          "pos": 4.395506340338596
        }, 
        {
          "dof": "tower_3", 
          "pos": 4.677684485355186
        }, 
        {
          "dof": "tower_2", 
          "pos": 4.762832998901123
        }, 
        {
          "dof": "base", 
          "pos": 2.9984511644195413
        }, 
        {
          "dof": "ears", 
          "pos": 5.0
        }
      ], 
      "millis": 516.0
    }, 
    {
      "positions": [
        {
          "dof": "tower_1", 
          "pos": 4.4942863701499665
        }, 
        {
          "dof": "tower_3", 
          "pos": 4.417646969195219
        }, 
        {
          "dof": "tower_2", 
          "pos": 4.924044185227426
        }, 
        {
          "dof": "base", 
          "pos": 3.3206195463802763
        }, 
        {
          "dof": "ears", 
          "pos": 5.0
        }
      ], 
      "millis": 620.0
    }, 
    {
      "positions": [
        {
          "dof": "tower_1", 
          "pos": 5.13598176660776
        }, 
        {
          "dof": "tower_3", 
          "pos": 3.1544488692549546
        }, 
        {
          "dof": "tower_2", 
          "pos": 5.5485544534164575
        }, 
        {
          "dof": "base", 
          "pos": 3.9590682218453193
        }, 
        {
          "dof": "ears", 
          "pos": 5.0
        }
      ], 
      "millis": 721.0
    }, 
    {
      "positions": [
        {
          "dof": "tower_1", 
          "pos": 5.642074180099878
        }, 
        {
          "dof": "tower_3", 
          "pos": 1.8780479859730839
        }, 
        {
          "dof": "tower_2", 
          "pos": 6.441559773911
        }, 
        {
          "dof": "base", 
          "pos": 4.653617948731121
        }, 
        {
          "dof": "ears", 
          "pos": 5.0
        }
      ], 
      "millis": 823.0
    }, 
    {
      "positions": [
        {
          "dof": "tower_1", 
          "pos": 5.743752001787712
        }, 
        {
          "dof": "tower_3", 
          "pos": 1.6730858541768703
        }, 
        {
          "dof": "tower_2", 
          "pos": 6.8076256831887125
        }, 
        {
          "dof": "base", 
          "pos": 5.080384322207101
        }, 
        {
          "dof": "ears", 
          "pos": 5.0
        }
      ], 
      "millis": 923.0
    }, 
    {
      "positions": [
        {
          "dof": "tower_1", 
          "pos": 5.839145696597514
        }, 
        {
          "dof": "tower_3", 
          "pos": 1.6598444342012373
        }, 
        {
          "dof": "tower_2", 
          "pos": 6.736493832023255
        }, 
        {
          "dof": "base", 
          "pos": 5.116449149896436
        }, 
        {
          "dof": "ears", 
          "pos": 5.0
        }
      ], 
      "millis": 1024.0
    }, 
    {
      "positions": [
        {
          "dof": "tower_1", 
          "pos": 6.239154985172556
        }, 
        {
          "dof": "tower_3", 
          "pos": 2.291364157403568
        }, 
        {
          "dof": "tower_2", 
          "pos": 5.456195441827994
        }, 
        {
          "dof": "base", 
          "pos": 4.400319035649402
        }, 
        {
          "dof": "ears", 
          "pos": 5.0
        }
      ], 
      "millis": 1124.0
    }, 
    {
      "positions": [
        {
          "dof": "tower_1", 
          "pos": 5.46066161106163
        }, 
        {
          "dof": "tower_3", 
          "pos": 3.635593197470841
        }, 
        {
          "dof": "tower_2", 
          "pos": 4.759276010548242
        }, 
        {
          "dof": "base", 
          "pos": 3.7485425017526692
        }, 
        {
          "dof": "ears", 
          "pos": 5.0
        }
      ], 
      "millis": 1227.0
    }, 
    {
      "positions": [
        {
          "dof": "tower_1", 
          "pos": 4.539767900976905
        }, 
        {
          "dof": "tower_3", 
          "pos": 4.586151424315428
        }, 
        {
          "dof": "tower_2", 
          "pos": 4.710073357160771
        }, 
        {
          "dof": "base", 
          "pos": 3.321970993800864
        }, 
        {
          "dof": "ears", 
          "pos": 5.0
        }
      ], 
      "millis": 1333.0
    }, 
    {
      "positions": [
        {
          "dof": "tower_1", 
          "pos": 4.107066749861545
        }, 
        {
          "dof": "tower_3", 
          "pos": 4.562387767147275
        }, 
        {
          "dof": "tower_2", 
          "pos": 5.160741344308753
        }, 
        {
          "dof": "base", 
          "pos": 2.9503778415720117
        }, 
        {
          "dof": "ears", 
          "pos": 5.0
        }
      ], 
      "millis": 1433.0
    }, 
    {
      "positions": [
        {
          "dof": "tower_1", 
          "pos": 3.8081772510495364
        }, 
        {
          "dof": "tower_3", 
          "pos": 4.66705888391529
        }, 
        {
          "dof": "tower_2", 
          "pos": 5.394842340399601
        }, 
        {
          "dof": "base", 
          "pos": 2.8086307605351677
        }, 
        {
          "dof": "ears", 
          "pos": 5.0
        }
      ], 
      "millis": 1534.0
    }, 
    {
      "positions": [
        {
          "dof": "tower_1", 
          "pos": 3.998896703856234
        }, 
        {
          "dof": "tower_3", 
          "pos": 4.746519975936754
        }, 
        {
          "dof": "tower_2", 
          "pos": 5.0919860157084145
        }, 
        {
          "dof": "base", 
          "pos": 2.5896167402434895
        }, 
        {
          "dof": "ears", 
          "pos": 5.0
        }
      ], 
      "millis": 1638.0
    }, 
    {
      "positions": [
        {
          "dof": "tower_1", 
          "pos": 4.677805164965097
        }, 
        {
          "dof": "tower_3", 
          "pos": 4.234146925474919
        }, 
        {
          "dof": "tower_2", 
          "pos": 4.924051715198566
        }, 
        {
          "dof": "base", 
          "pos": 2.0144100081582694
        }, 
        {
          "dof": "ears", 
          "pos": 5.0
        }
      ], 
      "millis": 1740.0
    }, 
    {
      "positions": [
        {
          "dof": "tower_1", 
          "pos": 5.555372649192401
        }, 
        {
          "dof": "tower_3", 
          "pos": 4.000017980694842
        }, 
        {
          "dof": "tower_2", 
          "pos": 4.279542784148871
        }, 
        {
          "dof": "base", 
          "pos": 1.3458773143099834
        }, 
        {
          "dof": "ears", 
          "pos": 5.0
        }
      ], 
      "millis": 1841.0
    }, 
    {
      "positions": [
        {
          "dof": "tower_1", 
          "pos": 6.167067486024303
        }, 
        {
          "dof": "tower_3", 
          "pos": 4.833694402962222
        }, 
        {
          "dof": "tower_2", 
          "pos": 3.034487633352417
        }, 
        {
          "dof": "base", 
          "pos": 0.7951468903019179
        }, 
        {
          "dof": "ears", 
          "pos": 5.0
        }
      ], 
      "millis": 1942.0
    }, 
    {
      "positions": [
        {
          "dof": "tower_1", 
          "pos": 5.667273019665179
        }, 
        {
          "dof": "tower_3", 
          "pos": 6.249422577690412
        }, 
        {
          "dof": "tower_2", 
          "pos": 2.008159910395022
        }, 
        {
          "dof": "base", 
          "pos": 0.20000000000000018
        }, 
        {
          "dof": "ears", 
          "pos": 5.0
        }
      ], 
      "millis": 2044.0
    }, 
    {
      "positions": [
        {
          "dof": "tower_1", 
          "pos": 5.667273019665179
        }, 
        {
          "dof": "tower_3", 
          "pos": 6.249422577690412
        }, 
        {
          "dof": "tower_2", 
          "pos": 2.008159910395022
        }, 
        {
          "dof": "base", 
          "pos": 0.20000000000000018
        }, 
        {
          "dof": "ears", 
          "pos": 5.0
        }
      ], 
      "millis": 2144.0
    }, 
    {
      "positions": [
        {
          "dof": "tower_1", 
          "pos": 5.030398293316491
        }, 
        {
          "dof": "tower_3", 
          "pos": 4.878592591547747
        }, 
        {
          "dof": "tower_2", 
          "pos": 3.9282478364323823
        }, 
        {
          "dof": "base", 
          "pos": 1.0708043931221738
        }, 
        {
          "dof": "ears", 
          "pos": 5.0
        }
      ], 
      "millis": 2244.0
    }, 
    {
      "positions": [
        {
          "dof": "tower_1", 
          "pos": 4.301753035067291
        }, 
        {
          "dof": "tower_3", 
          "pos": 4.5969701823746725
        }, 
        {
          "dof": "tower_2", 
          "pos": 4.934842425536015
        }, 
        {
          "dof": "base", 
          "pos": 1.5653784365067804
        }, 
        {
          "dof": "ears", 
          "pos": 5.0
        }
      ], 
      "millis": 2347.0
    }, 
    {
      "positions": [
        {
          "dof": "tower_1", 
          "pos": 3.414318127750908
        }, 
        {
          "dof": "tower_3", 
          "pos": 4.8712157440345365
        }, 
        {
          "dof": "tower_2", 
          "pos": 5.562457612583221
        }, 
        {
          "dof": "base", 
          "pos": 2.177280884231058
        }, 
        {
          "dof": "ears", 
          "pos": 5.0
        }
      ], 
      "millis": 2447.0
    }, 
    {
      "positions": [
        {
          "dof": "tower_1", 
          "pos": 3.3217037989561193
        }, 
        {
          "dof": "tower_3", 
          "pos": 4.972843085390264
        }, 
        {
          "dof": "tower_2", 
          "pos": 5.548842342938233
        }, 
        {
          "dof": "base", 
          "pos": 2.769864091273338
        }, 
        {
          "dof": "ears", 
          "pos": 5.0
        }
      ], 
      "millis": 2547.0
    }, 
    {
      "positions": [
        {
          "dof": "tower_1", 
          "pos": 3.6440058358726715
        }, 
        {
          "dof": "tower_3", 
          "pos": 4.917622790688468
        }, 
        {
          "dof": "tower_2", 
          "pos": 5.276288243779915
        }, 
        {
          "dof": "base", 
          "pos": 3.030777781637048
        }, 
        {
          "dof": "ears", 
          "pos": 5.0
        }
      ], 
      "millis": 2653.0
    }, 
    {
      "positions": [
        {
          "dof": "tower_1", 
          "pos": 4.0252982293700725
        }, 
        {
          "dof": "tower_3", 
          "pos": 4.866932249904846
        }, 
        {
          "dof": "tower_2", 
          "pos": 4.943815135549184
        }, 
        {
          "dof": "base", 
          "pos": 3.0815196086984464
        }, 
        {
          "dof": "ears", 
          "pos": 5.0
        }
      ], 
      "millis": 2756.0
    }, 
    {
      "positions": [
        {
          "dof": "tower_1", 
          "pos": 4.444155380081932
        }, 
        {
          "dof": "tower_3", 
          "pos": 4.678743545516156
        }, 
        {
          "dof": "tower_2", 
          "pos": 4.713103725360973
        }, 
        {
          "dof": "base", 
          "pos": 3.0751015595227376
        }, 
        {
          "dof": "ears", 
          "pos": 5.0
        }
      ], 
      "millis": 2858.0
    }, 
    {
      "positions": [
        {
          "dof": "tower_1", 
          "pos": 4.747278439030259
        }, 
        {
          "dof": "tower_3", 
          "pos": 4.5521141342627045
        }, 
        {
          "dof": "tower_2", 
          "pos": 4.536607004347816
        }, 
        {
          "dof": "base", 
          "pos": 3.121190439113114
        }, 
        {
          "dof": "ears", 
          "pos": 5.0
        }
      ], 
      "millis": 2959.0
    }, 
    {
      "positions": [
        {
          "dof": "tower_1", 
          "pos": 4.852152802803634
        }, 
        {
          "dof": "tower_3", 
          "pos": 4.4612341533806905
        }, 
        {
          "dof": "tower_2", 
          "pos": 4.522600630245052
        }, 
        {
          "dof": "base", 
          "pos": 3.141187233393956
        }, 
        {
          "dof": "ears", 
          "pos": 5.0
        }
      ], 
      "millis": 3062.0
    }, 
    {
      "positions": [
        {
          "dof": "tower_1", 
          "pos": 4.809819149695658
        }, 
        {
          "dof": "tower_3", 
          "pos": 4.417971245991854
        }, 
        {
          "dof": "tower_2", 
          "pos": 4.607137802734706
        }, 
        {
          "dof": "base", 
          "pos": 3.1282117340029685
        }, 
        {
          "dof": "ears", 
          "pos": 5.0
        }
      ], 
      "millis": 3167.0
    }, 
    {
      "positions": [
        {
          "dof": "tower_1", 
          "pos": 4.87521490907735
        }, 
        {
          "dof": "tower_3", 
          "pos": 4.385225319205624
        }, 
        {
          "dof": "tower_2", 
          "pos": 4.575303796294995
        }, 
        {
          "dof": "base", 
          "pos": 3.1184115828325596
        }, 
        {
          "dof": "ears", 
          "pos": 5.0
        }
      ], 
      "millis": 3269.0
    }, 
    {
      "positions": [
        {
          "dof": "tower_1", 
          "pos": 4.9185593033581405
        }, 
        {
          "dof": "tower_3", 
          "pos": 4.40257073968629
        }, 
        {
          "dof": "tower_2", 
          "pos": 4.514812636410995
        }, 
        {
          "dof": "base", 
          "pos": 3.1150760084184426
        }, 
        {
          "dof": "ears", 
          "pos": 5.0
        }
      ], 
      "millis": 3372.0
    }, 
    {
      "positions": [
        {
          "dof": "tower_1", 
          "pos": 4.868702244119157
        }, 
        {
          "dof": "tower_3", 
          "pos": 4.4096360369296566
        }, 
        {
          "dof": "tower_2", 
          "pos": 4.557553623912529
        }, 
        {
          "dof": "base", 
          "pos": 3.114942873190061
        }, 
        {
          "dof": "ears", 
          "pos": 5.0
        }
      ], 
      "millis": 3476.0
    }, 
    {
      "positions": [
        {
          "dof": "tower_1", 
          "pos": 4.853048281408187
        }, 
        {
          "dof": "tower_3", 
          "pos": 4.382907483226647
        }, 
        {
          "dof": "tower_2", 
          "pos": 4.599292782220288
        }, 
        {
          "dof": "base", 
          "pos": 3.1110856560533016
        }, 
        {
          "dof": "ears", 
          "pos": 5.0
        }
      ], 
      "millis": 3580.0
    }
  ], 
  "label": "none"
}