{"animation": "anger_20181204_130211", "frame_list": [{"positions": [{"dof": "tower_1", "pos": 5.57952338268028}, {"dof": "tower_3", "pos": 5.517568420836842}, {"dof": "tower_2", "pos": 2.7464177100059994}, {"dof": "base", "pos": 3.521256678208412}, {"dof": "ears", "pos": 4.78}], "millis": 146.0}, {"positions": [{"dof": "tower_1", "pos": 5.57952338268028}, {"dof": "tower_3", "pos": 5.517568420836842}, {"dof": "tower_2", "pos": 2.7464177100059994}, {"dof": "base", "pos": 3.521256678208412}, {"dof": "ears", "pos": 4.78}], "millis": 246.0}, {"positions": [{"dof": "tower_1", "pos": 5.546827882747106}, {"dof": "tower_3", "pos": 5.504309081675812}, {"dof": "tower_2", "pos": 2.7915409702261376}, {"dof": "base", "pos": 3.561020127103258}, {"dof": "ears", "pos": 4.78}], "millis": 347.0}, {"positions": [{"dof": "tower_1", "pos": 5.531656191846064}, {"dof": "tower_3", "pos": 5.478243640839455}, {"dof": "tower_2", "pos": 2.8323968820017074}, {"dof": "base", "pos": 3.5792291382229457}, {"dof": "ears", "pos": 4.78}], "millis": 447.0}, {"positions": [{"dof": "tower_1", "pos": 5.521823803671209}, {"dof": "tower_3", "pos": 5.509086428713284}, {"dof": "tower_2", "pos": 2.8111954759664557}, {"dof": "base", "pos": 3.576306500277097}, {"dof": "ears", "pos": 4.78}], "millis": 548.0}, {"positions": [{"dof": "tower_1", "pos": 5.5053684342506966}, {"dof": "tower_3", "pos": 5.466053435827599}, {"dof": "tower_2", "pos": 2.8702849028857833}, {"dof": "base", "pos": 3.5792474431299213}, {"dof": "ears", "pos": 4.78}], "millis": 650.0}, {"positions": [{"dof": "tower_1", "pos": 5.473144427030714}, {"dof": "tower_3", "pos": 5.449881236031635}, {"dof": "tower_2", "pos": 2.9180147744543485}, {"dof": "base", "pos": 3.5937144668109253}, {"dof": "ears", "pos": 4.78}], "millis": 751.0}, {"positions": [{"dof": "tower_1", "pos": 5.464711926996799}, {"dof": "tower_3", "pos": 5.428013348826939}, {"dof": "tower_2", "pos": 2.9481403634567918}, {"dof": "base", "pos": 3.5837020925066034}, {"dof": "ears", "pos": 4.78}], "millis": 851.0}, {"positions": [{"dof": "tower_1", "pos": 5.4818550723352555}, {"dof": "tower_3", "pos": 5.261429635210556}, {"dof": "tower_2", "pos": 3.097890116854088}, {"dof": "base", "pos": 3.5562598950631097}, {"dof": "ears", "pos": 4.78}], "millis": 952.0}, {"positions": [{"dof": "tower_1", "pos": 5.474003567007774}, {"dof": "tower_3", "pos": 5.00846713623546}, {"dof": "tower_2", "pos": 3.358978765826021}, {"dof": "base", "pos": 3.5161389540671046}, {"dof": "ears", "pos": 4.78}], "millis": 1052.0}, {"positions": [{"dof": "tower_1", "pos": 5.405972428314148}, {"dof": "tower_3", "pos": 4.903485357258511}, {"dof": "tower_2", "pos": 3.5310725856191563}, {"dof": "base", "pos": 3.549859734603241}, {"dof": "ears", "pos": 4.78}], "millis": 1154.0}, {"positions": [{"dof": "tower_1", "pos": 5.405972428314148}, {"dof": "tower_3", "pos": 4.903485357258511}, {"dof": "tower_2", "pos": 3.5310725856191563}, {"dof": "base", "pos": 3.549859734603241}, {"dof": "ears", "pos": 4.78}], "millis": 1254.0}, {"positions": [{"dof": "tower_1", "pos": 6.4856894356279575}, {"dof": "tower_3", "pos": 4.25932514458408}, {"dof": "tower_2", "pos": 3.0621196652499942}, {"dof": "base", "pos": 3.4347670855788075}, {"dof": "ears", "pos": 4.78}], "millis": 1355.0}, {"positions": [{"dof": "tower_1", "pos": 6.4856894356279575}, {"dof": "tower_3", "pos": 4.25932514458408}, {"dof": "tower_2", "pos": 3.0621196652499942}, {"dof": "base", "pos": 3.4347670855788075}, {"dof": "ears", "pos": 4.78}], "millis": 1456.0}, {"positions": [{"dof": "tower_1", "pos": 7.967383333053444}, {"dof": "tower_3", "pos": 3.5922366878662215}, {"dof": "tower_2", "pos": 2.2222235831978687}, {"dof": "base", "pos": 3.1911238559969144}, {"dof": "ears", "pos": 4.78}], "millis": 1557.0}, {"positions": [{"dof": "tower_1", "pos": 8.235294117647058}, {"dof": "tower_3", "pos": 3.3021485915868523}, {"dof": "tower_2", "pos": 1.6775557374146888}, {"dof": "base", "pos": 3.136873029457337}, {"dof": "ears", "pos": 4.78}], "millis": 1657.0}, {"positions": [{"dof": "tower_1", "pos": 8.235294117647058}, {"dof": "tower_3", "pos": 3.146448326216343}, {"dof": "tower_2", "pos": 1.3120462380494944}, {"dof": "base", "pos": 3.118965093076264}, {"dof": "ears", "pos": 4.78}], "millis": 1759.0}, {"positions": [{"dof": "tower_1", "pos": 8.235294117647058}, {"dof": "tower_3", "pos": 3.1956351765314115}, {"dof": "tower_2", "pos": 0.73611707271098}, {"dof": "base", "pos": 2.866583387772148}, {"dof": "ears", "pos": 4.78}], "millis": 1860.0}, {"positions": [{"dof": "tower_1", "pos": 8.235294117647058}, {"dof": "tower_3", "pos": 6.108802585885956}, {"dof": "tower_2", "pos": 0.3551632698682732}, {"dof": "base", "pos": 2.617597925730929}, {"dof": "ears", "pos": 4.78}], "millis": 1960.0}, {"positions": [{"dof": "tower_1", "pos": 8.235294117647058}, {"dof": "tower_3", "pos": 7.1365571406389305}, {"dof": "tower_2", "pos": -0.22250793764870247}, {"dof": "base", "pos": 1.7855551004865082}, {"dof": "ears", "pos": 4.78}], "millis": 2062.0}, {"positions": [{"dof": "tower_1", "pos": 8.235294117647058}, {"dof": "tower_3", "pos": 7.425200425754183}, {"dof": "tower_2", "pos": -0.23529411764705932}, {"dof": "base", "pos": 1.4813248891809943}, {"dof": "ears", "pos": 4.78}], "millis": 2164.0}, {"positions": [{"dof": "tower_1", "pos": 8.235294117647058}, {"dof": "tower_3", "pos": 6.083617243248282}, {"dof": "tower_2", "pos": 0.39806914620510936}, {"dof": "base", "pos": 2.6246328156703673}, {"dof": "ears", "pos": 4.78}], "millis": 2266.0}, {"positions": [{"dof": "tower_1", "pos": 8.072689563332311}, {"dof": "tower_3", "pos": 3.511803365303123}, {"dof": "tower_2", "pos": 2.2017729671680506}, {"dof": "base", "pos": 1.4813248891809943}, {"dof": "ears", "pos": 4.78}], "millis": 2367.0}, {"positions": [{"dof": "tower_1", "pos": 5.509120699102804}, {"dof": "tower_3", "pos": 4.469288910096598}, {"dof": "tower_2", "pos": 3.853835874055721}, {"dof": "base", "pos": 4.016182430751291}, {"dof": "ears", "pos": 4.78}], "millis": 2467.0}, {"positions": [{"dof": "tower_1", "pos": 4.276960562920474}, {"dof": "tower_3", "pos": 5.046363669874967}, {"dof": "tower_2", "pos": 4.512319811525494}, {"dof": "base", "pos": 4.1377479134483615}, {"dof": "ears", "pos": 4.78}], "millis": 2569.0}, {"positions": [{"dof": "tower_1", "pos": 4.276960562920474}, {"dof": "tower_3", "pos": 5.046363669874967}, {"dof": "tower_2", "pos": 4.512319811525494}, {"dof": "base", "pos": 4.1377479134483615}, {"dof": "ears", "pos": 4.78}], "millis": 2670.0}, {"positions": [{"dof": "tower_1", "pos": 4.175335262860667}, {"dof": "tower_3", "pos": 5.1843730494961004}, {"dof": "tower_2", "pos": 4.4755165826557555}, {"dof": "base", "pos": 4.065531776938683}, {"dof": "ears", "pos": 4.78}], "millis": 2769.0}, {"positions": [{"dof": "tower_1", "pos": 4.286243021823548}, {"dof": "tower_3", "pos": 5.274429974172742}, {"dof": "tower_2", "pos": 4.275099988233951}, {"dof": "base", "pos": 3.9865958271159796}, {"dof": "ears", "pos": 4.78}], "millis": 2871.0}, {"positions": [{"dof": "tower_1", "pos": 4.125136903918339}, {"dof": "tower_3", "pos": 5.446950395592485}, {"dof": "tower_2", "pos": 4.263087291356682}, {"dof": "base", "pos": 4.0062386315462355}, {"dof": "ears", "pos": 4.78}], "millis": 2972.0}, {"positions": [{"dof": "tower_1", "pos": 4.125136903918339}, {"dof": "tower_3", "pos": 5.446950395592485}, {"dof": "tower_2", "pos": 4.263087291356682}, {"dof": "base", "pos": 4.0062386315462355}, {"dof": "ears", "pos": 4.78}], "millis": 3074.0}, {"positions": [{"dof": "tower_1", "pos": 3.648842440022033}, {"dof": "tower_3", "pos": 5.5840237567384285}, {"dof": "tower_2", "pos": 4.560171652097626}, {"dof": "base", "pos": 4.148435247046464}, {"dof": "ears", "pos": 4.78}], "millis": 3177.0}, {"positions": [{"dof": "tower_1", "pos": 2.9296205000045363}, {"dof": "tower_3", "pos": 5.920246151354684}, {"dof": "tower_2", "pos": 4.998610755881416}, {"dof": "base", "pos": 4.307540952063542}, {"dof": "ears", "pos": 4.78}], "millis": 3279.0}, {"positions": [{"dof": "tower_1", "pos": 2.9296205000045363}, {"dof": "tower_3", "pos": 5.920246151354684}, {"dof": "tower_2", "pos": 4.998610755881416}, {"dof": "base", "pos": 4.307540952063542}, {"dof": "ears", "pos": 4.78}], "millis": 3380.0}, {"positions": [{"dof": "tower_1", "pos": 1.0462564466545785}, {"dof": "tower_3", "pos": 6.914857936913588}, {"dof": "tower_2", "pos": 5.902658977574363}, {"dof": "base", "pos": 4.578608757200872}, {"dof": "ears", "pos": 4.78}], "millis": 3481.0}, {"positions": [{"dof": "tower_1", "pos": 1.0462564466545785}, {"dof": "tower_3", "pos": 6.914857936913588}, {"dof": "tower_2", "pos": 5.902658977574363}, {"dof": "base", "pos": 4.578608757200872}, {"dof": "ears", "pos": 4.78}], "millis": 3582.0}, {"positions": [{"dof": "tower_1", "pos": 0.8293580113836341}, {"dof": "tower_3", "pos": 6.972215507411763}, {"dof": "tower_2", "pos": 6.0581873327463}, {"dof": "base", "pos": 4.569405760313196}, {"dof": "ears", "pos": 4.78}], "millis": 3684.0}, {"positions": [{"dof": "tower_1", "pos": 0.5931932997876981}, {"dof": "tower_3", "pos": 7.148519775142955}, {"dof": "tower_2", "pos": 6.127216985306194}, {"dof": "base", "pos": 4.64331387128407}, {"dof": "ears", "pos": 4.78}], "millis": 3785.0}, {"positions": [{"dof": "tower_1", "pos": 0.34747837162829853}, {"dof": "tower_3", "pos": 7.260286585545743}, {"dof": "tower_2", "pos": 6.262192319247944}, {"dof": "base", "pos": 4.691843731374845}, {"dof": "ears", "pos": 4.78}], "millis": 3889.0}, {"positions": [{"dof": "tower_1", "pos": 0.3330987623856312}, {"dof": "tower_3", "pos": 7.33168678324061}, {"dof": "tower_2", "pos": 6.215142727555295}, {"dof": "base", "pos": 4.715711417618104}, {"dof": "ears", "pos": 4.78}], "millis": 3990.0}, {"positions": [{"dof": "tower_1", "pos": 0.3330987623856312}, {"dof": "tower_3", "pos": 7.33168678324061}, {"dof": "tower_2", "pos": 6.215142727555295}, {"dof": "base", "pos": 4.715711417618104}, {"dof": "ears", "pos": 4.78}], "millis": 4091.0}, {"positions": [{"dof": "tower_1", "pos": 0.37205691802704344}, {"dof": "tower_3", "pos": 7.705534315443315}, {"dof": "tower_2", "pos": 5.903882602620369}, {"dof": "base", "pos": 4.893485395674661}, {"dof": "ears", "pos": 4.78}], "millis": 4192.0}, {"positions": [{"dof": "tower_1", "pos": 0.37205691802704344}, {"dof": "tower_3", "pos": 7.705534315443315}, {"dof": "tower_2", "pos": 5.903882602620369}, {"dof": "base", "pos": 4.893485395674661}, {"dof": "ears", "pos": 4.78}], "millis": 4292.0}, {"positions": [{"dof": "tower_1", "pos": 1.3603959976831186}, {"dof": "tower_3", "pos": 7.375161645227072}, {"dof": "tower_2", "pos": 5.300070809183326}, {"dof": "base", "pos": 4.777091868820907}, {"dof": "ears", "pos": 4.78}], "millis": 4396.0}, {"positions": [{"dof": "tower_1", "pos": 1.8626100436181894}, {"dof": "tower_3", "pos": 7.193082316174573}, {"dof": "tower_2", "pos": 5.0568064433529525}, {"dof": "base", "pos": 4.688609226991494}, {"dof": "ears", "pos": 4.78}], "millis": 4496.0}, {"positions": [{"dof": "tower_1", "pos": 1.8626100436181894}, {"dof": "tower_3", "pos": 7.193082316174573}, {"dof": "tower_2", "pos": 5.0568064433529525}, {"dof": "base", "pos": 4.688609226991494}, {"dof": "ears", "pos": 4.78}], "millis": 4598.0}, {"positions": [{"dof": "tower_1", "pos": 2.152691680635532}, {"dof": "tower_3", "pos": 6.409779716746401}, {"dof": "tower_2", "pos": 5.298229958150593}, {"dof": "base", "pos": 4.421134374565158}, {"dof": "ears", "pos": 4.78}], "millis": 4699.0}, {"positions": [{"dof": "tower_1", "pos": 3.200397628662365}, {"dof": "tower_3", "pos": 5.218226938135239}, {"dof": "tower_2", "pos": 5.417709775302041}, {"dof": "base", "pos": 4.054817122583901}, {"dof": "ears", "pos": 4.78}], "millis": 4799.0}, {"positions": [{"dof": "tower_1", "pos": 4.780148434864158}, {"dof": "tower_3", "pos": 4.24034903742131}, {"dof": "tower_2", "pos": 4.815532417570929}, {"dof": "base", "pos": 3.7204699370507224}, {"dof": "ears", "pos": 4.78}], "millis": 4901.0}, {"positions": [{"dof": "tower_1", "pos": 5.986989878235601}, {"dof": "tower_3", "pos": 3.8185617252268407}, {"dof": "tower_2", "pos": 4.030081217285024}, {"dof": "base", "pos": 3.538373951891164}, {"dof": "ears", "pos": 4.78}], "millis": 5006.0}, {"positions": [{"dof": "tower_1", "pos": 6.763793313044138}, {"dof": "tower_3", "pos": 3.5959355018772445}, {"dof": "tower_2", "pos": 3.4760847812965396}, {"dof": "base", "pos": 3.4318906197117482}, {"dof": "ears", "pos": 4.78}], "millis": 5107.0}, {"positions": [{"dof": "tower_1", "pos": 7.124580974313575}, {"dof": "tower_3", "pos": 3.562266247880829}, {"dof": "tower_2", "pos": 3.1463926587948263}, {"dof": "base", "pos": 3.3624866086871474}, {"dof": "ears", "pos": 4.78}], "millis": 5208.0}, {"positions": [{"dof": "tower_1", "pos": 7.104242936347056}, {"dof": "tower_3", "pos": 3.948418082173758}, {"dof": "tower_2", "pos": 2.7530590342421997}, {"dof": "base", "pos": 3.316828160123446}, {"dof": "ears", "pos": 4.78}], "millis": 5309.0}, {"positions": [{"dof": "tower_1", "pos": 6.813150162006415}, {"dof": "tower_3", "pos": 4.335534453202039}, {"dof": "tower_2", "pos": 2.4843797945366357}, {"dof": "base", "pos": 3.3198938222305148}, {"dof": "ears", "pos": 4.78}], "millis": 5411.0}, {"positions": [{"dof": "tower_1", "pos": 6.813150162006415}, {"dof": "tower_3", "pos": 4.335534453202039}, {"dof": "tower_2", "pos": 2.4843797945366357}, {"dof": "base", "pos": 3.3198938222305148}, {"dof": "ears", "pos": 4.78}], "millis": 5512.0}, {"positions": [{"dof": "tower_1", "pos": 5.662549605404775}, {"dof": "tower_3", "pos": 5.624573463483566}, {"dof": "tower_2", "pos": 2.5590188225249024}, {"dof": "base", "pos": 3.4833289109548975}, {"dof": "ears", "pos": 4.78}], "millis": 5613.0}, {"positions": [{"dof": "tower_1", "pos": 5.662549605404775}, {"dof": "tower_3", "pos": 5.624573463483566}, {"dof": "tower_2", "pos": 2.5590188225249024}, {"dof": "base", "pos": 3.4833289109548975}, {"dof": "ears", "pos": 4.78}], "millis": 5713.0}, {"positions": [{"dof": "tower_1", "pos": 4.626248550358392}, {"dof": "tower_3", "pos": 6.337811378419535}, {"dof": "tower_2", "pos": 2.871940095848847}, {"dof": "base", "pos": 3.811235228100754}, {"dof": "ears", "pos": 4.78}], "millis": 5818.0}, {"positions": [{"dof": "tower_1", "pos": 4.2425071827714405}, {"dof": "tower_3", "pos": 6.541010792385393}, {"dof": "tower_2", "pos": 3.052045244346037}, {"dof": "base", "pos": 3.9471950612660605}, {"dof": "ears", "pos": 4.78}], "millis": 5919.0}, {"positions": [{"dof": "tower_1", "pos": 4.2425071827714405}, {"dof": "tower_3", "pos": 6.541010792385393}, {"dof": "tower_2", "pos": 3.052045244346037}, {"dof": "base", "pos": 3.9471950612660605}, {"dof": "ears", "pos": 4.78}], "millis": 6019.0}, {"positions": [{"dof": "tower_1", "pos": 3.55417027637403}, {"dof": "tower_3", "pos": 6.736883705580072}, {"dof": "tower_2", "pos": 3.534374635065097}, {"dof": "base", "pos": 4.266118586823083}, {"dof": "ears", "pos": 4.78}], "millis": 6123.0}, {"positions": [{"dof": "tower_1", "pos": 3.5629938892983692}, {"dof": "tower_3", "pos": 6.643199335515085}, {"dof": "tower_2", "pos": 3.619765922414405}, {"dof": "base", "pos": 4.2682184601815125}, {"dof": "ears", "pos": 4.78}], "millis": 6223.0}, {"positions": [{"dof": "tower_1", "pos": 3.5629938892983692}, {"dof": "tower_3", "pos": 6.643199335515085}, {"dof": "tower_2", "pos": 3.619765922414405}, {"dof": "base", "pos": 4.2682184601815125}, {"dof": "ears", "pos": 4.78}], "millis": 6324.0}, {"positions": [{"dof": "tower_1", "pos": 3.6715011132954847}, {"dof": "tower_3", "pos": 6.5156480342749346}, {"dof": "tower_2", "pos": 3.641930150847595}, {"dof": "base", "pos": 4.270109876166472}, {"dof": "ears", "pos": 4.78}], "millis": 6425.0}, {"positions": [{"dof": "tower_1", "pos": 3.6715011132954847}, {"dof": "tower_3", "pos": 6.5156480342749346}, {"dof": "tower_2", "pos": 3.641930150847595}, {"dof": "base", "pos": 4.270109876166472}, {"dof": "ears", "pos": 4.78}], "millis": 6526.0}, {"positions": [{"dof": "tower_1", "pos": 3.6715011132954847}, {"dof": "tower_3", "pos": 6.5156480342749346}, {"dof": "tower_2", "pos": 3.641930150847595}, {"dof": "base", "pos": 4.270109876166472}, {"dof": "ears", "pos": 4.78}], "millis": 6626.0}, {"positions": [{"dof": "tower_1", "pos": 5.678229041117018}, {"dof": "tower_3", "pos": 5.19324059594066}, {"dof": "tower_2", "pos": 2.9749823768318273}, {"dof": "base", "pos": 3.7322756458235222}, {"dof": "ears", "pos": 4.78}], "millis": 6726.0}, {"positions": [{"dof": "tower_1", "pos": 5.678229041117018}, {"dof": "tower_3", "pos": 5.19324059594066}, {"dof": "tower_2", "pos": 2.9749823768318273}, {"dof": "base", "pos": 3.7322756458235222}, {"dof": "ears", "pos": 4.78}], "millis": 6828.0}, {"positions": [{"dof": "tower_1", "pos": 5.678229041117018}, {"dof": "tower_3", "pos": 5.19324059594066}, {"dof": "tower_2", "pos": 2.9749823768318273}, {"dof": "base", "pos": 3.7322756458235222}, {"dof": "ears", "pos": 4.78}], "millis": 6929.0}, {"positions": [{"dof": "tower_1", "pos": 4.793931234837385}, {"dof": "tower_3", "pos": 5.513975183880935}, {"dof": "tower_2", "pos": 3.5281326894156924}, {"dof": "base", "pos": 3.95918272627835}, {"dof": "ears", "pos": 4.78}], "millis": 7029.0}, {"positions": [{"dof": "tower_1", "pos": 4.794265256361452}, {"dof": "tower_3", "pos": 5.2794365795595155}, {"dof": "tower_2", "pos": 3.7623357125374945}, {"dof": "base", "pos": 4.0499174180809}, {"dof": "ears", "pos": 4.78}], "millis": 7139.0}, {"positions": [{"dof": "tower_1", "pos": 4.794265256361452}, {"dof": "tower_3", "pos": 5.2794365795595155}, {"dof": "tower_2", "pos": 3.7623357125374945}, {"dof": "base", "pos": 4.0499174180809}, {"dof": "ears", "pos": 4.78}], "millis": 7240.0}, {"positions": [{"dof": "tower_1", "pos": 6.538909171731122}, {"dof": "tower_3", "pos": 4.941256082040859}, {"dof": "tower_2", "pos": 2.4743310302600072}, {"dof": "base", "pos": 3.462055876973543}, {"dof": "ears", "pos": 4.78}], "millis": 7341.0}, {"positions": [{"dof": "tower_1", "pos": 6.572581987713148}, {"dof": "tower_3", "pos": 4.39394125144544}, {"dof": "tower_2", "pos": 2.718867032341384}, {"dof": "base", "pos": 3.5536164752505313}, {"dof": "ears", "pos": 4.78}], "millis": 7440.0}, {"positions": [{"dof": "tower_1", "pos": 4.663958355358177}, {"dof": "tower_3", "pos": 4.990365340901135}, {"dof": "tower_2", "pos": 4.181677121605043}, {"dof": "base", "pos": 4.217907559962765}, {"dof": "ears", "pos": 4.78}], "millis": 7542.0}, {"positions": [{"dof": "tower_1", "pos": 4.954760699499501}, {"dof": "tower_3", "pos": 4.970863150366522}, {"dof": "tower_2", "pos": 3.9106411151240135}, {"dof": "base", "pos": 4.215655783197195}, {"dof": "ears", "pos": 4.78}], "millis": 7643.0}, {"positions": [{"dof": "tower_1", "pos": 6.949761861960234}, {"dof": "tower_3", "pos": 4.943657876139021}, {"dof": "tower_2", "pos": 2.247758713048417}, {"dof": "base", "pos": 3.438570681323804}, {"dof": "ears", "pos": 4.78}], "millis": 7743.0}, {"positions": [{"dof": "tower_1", "pos": 6.949761861960234}, {"dof": "tower_3", "pos": 4.943657876139021}, {"dof": "tower_2", "pos": 2.247758713048417}, {"dof": "base", "pos": 3.438570681323804}, {"dof": "ears", "pos": 4.78}], "millis": 7843.0}, {"positions": [{"dof": "tower_1", "pos": 5.2658921502012515}, {"dof": "tower_3", "pos": 4.741411659129175}, {"dof": "tower_2", "pos": 3.8320655972905904}, {"dof": "base", "pos": 4.015274971818163}, {"dof": "ears", "pos": 4.78}], "millis": 7944.0}, {"positions": [{"dof": "tower_1", "pos": 3.574328528212301}, {"dof": "tower_3", "pos": 5.2937595473568555}, {"dof": "tower_2", "pos": 4.9686158945720775}, {"dof": "base", "pos": 4.443180585960559}, {"dof": "ears", "pos": 4.78}], "millis": 8045.0}, {"positions": [{"dof": "tower_1", "pos": 3.574328528212301}, {"dof": "tower_3", "pos": 5.2937595473568555}, {"dof": "tower_2", "pos": 4.9686158945720775}, {"dof": "base", "pos": 4.443180585960559}, {"dof": "ears", "pos": 4.78}], "millis": 8144.0}, {"positions": [{"dof": "tower_1", "pos": 5.006579355459012}, {"dof": "tower_3", "pos": 4.4087181426328135}, {"dof": "tower_2", "pos": 4.420702178489687}, {"dof": "base", "pos": 4.083937497506467}, {"dof": "ears", "pos": 4.78}], "millis": 8248.0}, {"positions": [{"dof": "tower_1", "pos": 5.826970295936571}, {"dof": "tower_3", "pos": 3.7754691032084886}, {"dof": "tower_2", "pos": 4.231840342957792}, {"dof": "base", "pos": 3.795146990718356}, {"dof": "ears", "pos": 4.78}], "millis": 8350.0}, {"positions": [{"dof": "tower_1", "pos": 5.826970295936571}, {"dof": "tower_3", "pos": 3.7754691032084886}, {"dof": "tower_2", "pos": 4.231840342957792}, {"dof": "base", "pos": 3.795146990718356}, {"dof": "ears", "pos": 4.78}], "millis": 8450.0}, {"positions": [{"dof": "tower_1", "pos": 1.9625219822156383}, {"dof": "tower_3", "pos": 6.174139261479031}, {"dof": "tower_2", "pos": 5.703129409215908}, {"dof": "base", "pos": 4.687642345412586}, {"dof": "ears", "pos": 4.78}], "millis": 8552.0}]}