{
  "animation": "yes_1", 
  "frame_list": [
    {
      "positions": [
        {
          "dof": "tower_1", 
          "pos": 4.3097594928527165
        }, 
        {
          "dof": "tower_3", 
          "pos": 3.8523007909481035
        }, 
        {
          "dof": "tower_2", 
          "pos": 3.837938894160035
        }, 
        {
          "dof": "base", 
          "pos": 3.049120351043849
        }, 
        {
          "dof": "ears", 
          "pos": 5.34
        }
      ], 
      "millis": 0.0
    }, 
    {
      "positions": [
        {
          "dof": "tower_1", 
          "pos": 4.3097594928527165
        }, 
        {
          "dof": "tower_3", 
          "pos": 3.8523007909481035
        }, 
        {
          "dof": "tower_2", 
          "pos": 3.837938894160035
        }, 
        {
          "dof": "base", 
          "pos": 3.049120351043849
        }, 
        {
          "dof": "ears", 
          "pos": 5.34
        }
      ], 
      "millis": 101.0
    }, 
    {
      "positions": [
        {
          "dof": "tower_1", 
          "pos": 4.306344978719753
        }, 
        {
          "dof": "tower_3", 
          "pos": 3.8546172737811384
        }, 
        {
          "dof": "tower_2", 
          "pos": 3.839036790337966
        }, 
        {
          "dof": "base", 
          "pos": 3.04909337185866
        }, 
        {
          "dof": "ears", 
          "pos": 5.34
        }
      ], 
      "millis": 202.0
    }, 
    {
      "positions": [
        {
          "dof": "tower_1", 
          "pos": 4.3258221019338725
        }, 
        {
          "dof": "tower_3", 
          "pos": 3.8614551229111154
        }, 
        {
          "dof": "tower_2", 
          "pos": 3.812712604874312
        }, 
        {
          "dof": "base", 
          "pos": 3.0528744343598078
        }, 
        {
          "dof": "ears", 
          "pos": 5.34
        }
      ], 
      "millis": 306.0
    }, 
    {
      "positions": [
        {
          "dof": "tower_1", 
          "pos": 4.327822617516128
        }, 
        {
          "dof": "tower_3", 
          "pos": 3.8600765603329483
        }, 
        {
          "dof": "tower_2", 
          "pos": 3.8120909141404447
        }, 
        {
          "dof": "base", 
          "pos": 3.0538056450340973
        }, 
        {
          "dof": "ears", 
          "pos": 5.34
        }
      ], 
      "millis": 406.0
    }, 
    {
      "positions": [
        {
          "dof": "tower_1", 
          "pos": 4.323194686718467
        }, 
        {
          "dof": "tower_3", 
          "pos": 3.8636143168202444
        }, 
        {
          "dof": "tower_2", 
          "pos": 3.813180174297208
        }, 
        {
          "dof": "base", 
          "pos": 3.0539081725309822
        }, 
        {
          "dof": "ears", 
          "pos": 5.34
        }
      ], 
      "millis": 507.0
    }, 
    {
      "positions": [
        {
          "dof": "tower_1", 
          "pos": 4.329661231040799
        }, 
        {
          "dof": "tower_3", 
          "pos": 3.862893078541816
        }, 
        {
          "dof": "tower_2", 
          "pos": 3.8074322852878337
        }, 
        {
          "dof": "base", 
          "pos": 3.0551578329069295
        }, 
        {
          "dof": "ears", 
          "pos": 5.34
        }
      ], 
      "millis": 608.0
    }, 
    {
      "positions": [
        {
          "dof": "tower_1", 
          "pos": 4.320933616396597
        }, 
        {
          "dof": "tower_3", 
          "pos": 3.872168204982396
        }, 
        {
          "dof": "tower_2", 
          "pos": 3.8068798475938124
        }, 
        {
          "dof": "base", 
          "pos": 3.0563090453385633
        }, 
        {
          "dof": "ears", 
          "pos": 5.34
        }
      ], 
      "millis": 710.0
    }, 
    {
      "positions": [
        {
          "dof": "tower_1", 
          "pos": 4.2470401524512
        }, 
        {
          "dof": "tower_3", 
          "pos": 3.9210375940672884
        }, 
        {
          "dof": "tower_2", 
          "pos": 3.8318932822657517
        }, 
        {
          "dof": "base", 
          "pos": 3.0583425039612466
        }, 
        {
          "dof": "ears", 
          "pos": 5.34
        }
      ], 
      "millis": 811.0
    }, 
    {
      "positions": [
        {
          "dof": "tower_1", 
          "pos": 4.112564597061512
        }, 
        {
          "dof": "tower_3", 
          "pos": 3.978262479128989
        }, 
        {
          "dof": "tower_2", 
          "pos": 3.909161869089661
        }, 
        {
          "dof": "base", 
          "pos": 3.0551407040292826
        }, 
        {
          "dof": "ears", 
          "pos": 5.34
        }
      ], 
      "millis": 912.0
    }, 
    {
      "positions": [
        {
          "dof": "tower_1", 
          "pos": 3.8152839352831274
        }, 
        {
          "dof": "tower_3", 
          "pos": 4.101130807142402
        }, 
        {
          "dof": "tower_2", 
          "pos": 4.0835859930405904
        }, 
        {
          "dof": "base", 
          "pos": 3.0382591396217853
        }, 
        {
          "dof": "ears", 
          "pos": 5.34
        }
      ], 
      "millis": 1015.0
    }, 
    {
      "positions": [
        {
          "dof": "tower_1", 
          "pos": 3.4868953927553825
        }, 
        {
          "dof": "tower_3", 
          "pos": 4.258134128537314
        }, 
        {
          "dof": "tower_2", 
          "pos": 4.2549705449218065
        }, 
        {
          "dof": "base", 
          "pos": 3.0144006382835786
        }, 
        {
          "dof": "ears", 
          "pos": 5.34
        }
      ], 
      "millis": 1118.0
    }, 
    {
      "positions": [
        {
          "dof": "tower_1", 
          "pos": 3.1679895636509783
        }, 
        {
          "dof": "tower_3", 
          "pos": 4.353167977375849
        }, 
        {
          "dof": "tower_2", 
          "pos": 4.479018539002824
        }, 
        {
          "dof": "base", 
          "pos": 2.9889118784505313
        }, 
        {
          "dof": "ears", 
          "pos": 5.34
        }
      ], 
      "millis": 1222.0
    }, 
    {
      "positions": [
        {
          "dof": "tower_1", 
          "pos": 3.46579985754362
        }, 
        {
          "dof": "tower_3", 
          "pos": 4.235366490886424
        }, 
        {
          "dof": "tower_2", 
          "pos": 4.298861844573619
        }, 
        {
          "dof": "base", 
          "pos": 3.03241760021671
        }, 
        {
          "dof": "ears", 
          "pos": 5.34
        }
      ], 
      "millis": 1325.0
    }, 
    {
      "positions": [
        {
          "dof": "tower_1", 
          "pos": 4.001153134319776
        }, 
        {
          "dof": "tower_3", 
          "pos": 4.01445741209384
        }, 
        {
          "dof": "tower_2", 
          "pos": 3.9843894536060507
        }, 
        {
          "dof": "base", 
          "pos": 3.0645480809182555
        }, 
        {
          "dof": "ears", 
          "pos": 5.34
        }
      ], 
      "millis": 1426.0
    }, 
    {
      "positions": [
        {
          "dof": "tower_1", 
          "pos": 4.496812314455678
        }, 
        {
          "dof": "tower_3", 
          "pos": 3.785339177243797
        }, 
        {
          "dof": "tower_2", 
          "pos": 3.7178187559008338
        }, 
        {
          "dof": "base", 
          "pos": 3.075839691813773
        }, 
        {
          "dof": "ears", 
          "pos": 5.34
        }
      ], 
      "millis": 1527.0
    }, 
    {
      "positions": [
        {
          "dof": "tower_1", 
          "pos": 4.980974716668528
        }, 
        {
          "dof": "tower_3", 
          "pos": 3.5973977915644495
        }, 
        {
          "dof": "tower_2", 
          "pos": 3.4212131814311832
        }, 
        {
          "dof": "base", 
          "pos": 3.090520027114549
        }, 
        {
          "dof": "ears", 
          "pos": 5.34
        }
      ], 
      "millis": 1628.0
    }, 
    {
      "positions": [
        {
          "dof": "tower_1", 
          "pos": 4.958700139198071
        }, 
        {
          "dof": "tower_3", 
          "pos": 3.6031895747004814
        }, 
        {
          "dof": "tower_2", 
          "pos": 3.4377547213192927
        }, 
        {
          "dof": "base", 
          "pos": 3.0877373088363753
        }, 
        {
          "dof": "ears", 
          "pos": 5.34
        }
      ], 
      "millis": 1731.0
    }, 
    {
      "positions": [
        {
          "dof": "tower_1", 
          "pos": 4.491483990113133
        }, 
        {
          "dof": "tower_3", 
          "pos": 3.8242473301799924
        }, 
        {
          "dof": "tower_2", 
          "pos": 3.6841331039663725
        }, 
        {
          "dof": "base", 
          "pos": 3.083149050367729
        }, 
        {
          "dof": "ears", 
          "pos": 5.34
        }
      ], 
      "millis": 1835.0
    }, 
    {
      "positions": [
        {
          "dof": "tower_1", 
          "pos": 3.9955745314313162
        }, 
        {
          "dof": "tower_3", 
          "pos": 4.03968159165556
        }, 
        {
          "dof": "tower_2", 
          "pos": 3.9647438757988427
        }, 
        {
          "dof": "base", 
          "pos": 3.0746970210553264
        }, 
        {
          "dof": "ears", 
          "pos": 5.34
        }
      ], 
      "millis": 1935.0
    }, 
    {
      "positions": [
        {
          "dof": "tower_1", 
          "pos": 3.298052854132806
        }, 
        {
          "dof": "tower_3", 
          "pos": 4.343190537205465
        }, 
        {
          "dof": "tower_2", 
          "pos": 4.358758816451181
        }, 
        {
          "dof": "base", 
          "pos": 3.023735218984523
        }, 
        {
          "dof": "ears", 
          "pos": 5.34
        }
      ], 
      "millis": 2036.0
    }, 
    {
      "positions": [
        {
          "dof": "tower_1", 
          "pos": 2.9646392190554334
        }, 
        {
          "dof": "tower_3", 
          "pos": 4.471488190686577
        }, 
        {
          "dof": "tower_2", 
          "pos": 4.563990278912477
        }, 
        {
          "dof": "base", 
          "pos": 2.995754688508644
        }, 
        {
          "dof": "ears", 
          "pos": 5.34
        }
      ], 
      "millis": 2139.0
    }, 
    {
      "positions": [
        {
          "dof": "tower_1", 
          "pos": 2.8426951719083795
        }, 
        {
          "dof": "tower_3", 
          "pos": 4.460774171411502
        }, 
        {
          "dof": "tower_2", 
          "pos": 4.6974323683217065
        }, 
        {
          "dof": "base", 
          "pos": 2.9790665948431783
        }, 
        {
          "dof": "ears", 
          "pos": 5.34
        }
      ], 
      "millis": 2239.0
    }, 
    {
      "positions": [
        {
          "dof": "tower_1", 
          "pos": 3.3508411625412773
        }, 
        {
          "dof": "tower_3", 
          "pos": 4.198873863709302
        }, 
        {
          "dof": "tower_2", 
          "pos": 4.450917321606739
        }, 
        {
          "dof": "base", 
          "pos": 3.0455194367841405
        }, 
        {
          "dof": "ears", 
          "pos": 5.34
        }
      ], 
      "millis": 2344.0
    }, 
    {
      "positions": [
        {
          "dof": "tower_1", 
          "pos": 4.011092420497384
        }, 
        {
          "dof": "tower_3", 
          "pos": 3.9238970381267113
        }, 
        {
          "dof": "tower_2", 
          "pos": 4.065010558987357
        }, 
        {
          "dof": "base", 
          "pos": 3.0923948896058717
        }, 
        {
          "dof": "ears", 
          "pos": 5.34
        }
      ], 
      "millis": 2444.0
    }, 
    {
      "positions": [
        {
          "dof": "tower_1", 
          "pos": 4.486583144066813
        }, 
        {
          "dof": "tower_3", 
          "pos": 3.715799993737519
        }, 
        {
          "dof": "tower_2", 
          "pos": 3.797573694483658
        }, 
        {
          "dof": "base", 
          "pos": 3.1088591244979846
        }, 
        {
          "dof": "ears", 
          "pos": 5.34
        }
      ], 
      "millis": 2545.0
    }, 
    {
      "positions": [
        {
          "dof": "tower_1", 
          "pos": 4.738516655570095
        }, 
        {
          "dof": "tower_3", 
          "pos": 3.6372124370729577
        }, 
        {
          "dof": "tower_2", 
          "pos": 3.6242692999637187
        }, 
        {
          "dof": "base", 
          "pos": 3.1207141561063554
        }, 
        {
          "dof": "ears", 
          "pos": 5.34
        }
      ], 
      "millis": 2646.0
    }, 
    {
      "positions": [
        {
          "dof": "tower_1", 
          "pos": 4.660765914383482
        }, 
        {
          "dof": "tower_3", 
          "pos": 3.704796341227392
        }, 
        {
          "dof": "tower_2", 
          "pos": 3.6343948225589386
        }, 
        {
          "dof": "base", 
          "pos": 3.116955346756869
        }, 
        {
          "dof": "ears", 
          "pos": 5.34
        }
      ], 
      "millis": 2747.0
    }, 
    {
      "positions": [
        {
          "dof": "tower_1", 
          "pos": 4.567675589713813
        }, 
        {
          "dof": "tower_3", 
          "pos": 3.7626929518445182
        }, 
        {
          "dof": "tower_2", 
          "pos": 3.66956607534188
        }, 
        {
          "dof": "base", 
          "pos": 3.116201044303479
        }, 
        {
          "dof": "ears", 
          "pos": 5.34
        }
      ], 
      "millis": 2851.0
    }, 
    {
      "positions": [
        {
          "dof": "tower_1", 
          "pos": 4.515711923556214
        }, 
        {
          "dof": "tower_3", 
          "pos": 3.7968770747565355
        }, 
        {
          "dof": "tower_2", 
          "pos": 3.687327335697632
        }, 
        {
          "dof": "base", 
          "pos": 3.1165779604422363
        }, 
        {
          "dof": "ears", 
          "pos": 5.34
        }
      ], 
      "millis": 2951.0
    }, 
    {
      "positions": [
        {
          "dof": "tower_1", 
          "pos": 4.3901861757304905
        }, 
        {
          "dof": "tower_3", 
          "pos": 3.852693880396348
        }, 
        {
          "dof": "tower_2", 
          "pos": 3.757071103611147
        }, 
        {
          "dof": "base", 
          "pos": 3.116365514187738
        }, 
        {
          "dof": "ears", 
          "pos": 5.34
        }
      ], 
      "millis": 3052.0
    }, 
    {
      "positions": [
        {
          "dof": "tower_1", 
          "pos": 4.338960645067236
        }, 
        {
          "dof": "tower_3", 
          "pos": 3.8715191983098696
        }, 
        {
          "dof": "tower_2", 
          "pos": 3.7894890193836206
        }, 
        {
          "dof": "base", 
          "pos": 3.1172286826682747
        }, 
        {
          "dof": "ears", 
          "pos": 5.34
        }
      ], 
      "millis": 3156.0
    }
  ], 
  "label": "none"
}